casper/__init__.py
casper/casper.py
casper/main.py
casper/terraform.py
casper/version.py
casper/services/__init__.py
casper/services/base.py
casper/services/ec2.py
casper/services/iam.py
casper/services/s3.py
casper/states/__init__.py
casper/states/aws.py
casper/states/terraform.py
aws_terraform_casper-0.3.0.dist-info/LICENSE
aws_terraform_casper-0.3.0.dist-info/METADATA
aws_terraform_casper-0.3.0.dist-info/WHEEL
aws_terraform_casper-0.3.0.dist-info/entry_points.txt
aws_terraform_casper-0.3.0.dist-info/top_level.txt
aws_terraform_casper-0.3.0.dist-info/RECORD
