Metadata-Version: 2.1
Name: aws-terraform-casper
Version: 0.3.0
Summary: A tool for detecting resources running on your AWS cloud environment but not provisioned through Terraform
Home-page: https://github.com/edeas123/aws-terraform-casper
Author: Obaro Odiete
Author-email: mybytesni@gmail.com
License: UNKNOWN
Platform: UNKNOWN
Classifier: Programming Language :: Python :: 3.6
Classifier: Programming Language :: Python :: 3.7
Classifier: License :: OSI Approved :: Mozilla Public License 2.0 (MPL 2.0)
Classifier: Operating System :: OS Independent
Requires-Python: >=3.6
Requires-Dist: boto3 (>=1.10.41)
Requires-Dist: docopt (>=0.6.2)
